equity_jenga/__init__.py
equity_jenga/api/__init__.py
equity_jenga/api/airtime.py
equity_jenga/api/auth.py
equity_jenga/api/errors.py
equity_jenga/api/exceptions.py
equity_jenga/api/forex.py
equity_jenga/api/helpers.py
equity_jenga/api/kyc.py
equity_jenga/api/loans.py
equity_jenga/api/account_services/__init__.py
equity_jenga/api/account_services/account_balances.py
equity_jenga/api/account_services/account_inquiries.py
equity_jenga/api/account_services/account_statements.py
equity_jenga/api/account_services/balances.py
equity_jenga/api/account_services/inquiries.py
equity_jenga/api/account_services/statements.py
equity_jenga/api/receive_money/LNMOnline.py
equity_jenga/api/receive_money/__init__.py
equity_jenga/api/receive_money/bill_payments.py
equity_jenga/api/receive_money/bill_validation.py
equity_jenga/api/receive_money/eazzypay_push.py
equity_jenga/api/receive_money/merchant_payments.py
equity_jenga/api/receive_money/queries.py
equity_jenga/api/receive_money/refund_payments.py
equity_jenga/api/send_money/EFT.py
equity_jenga/api/send_money/RTGS.py
equity_jenga/api/send_money/SWIFT.py
equity_jenga/api/send_money/__init__.py
equity_jenga/api/send_money/pesalink_to_bank.py
equity_jenga/api/send_money/pesalink_to_mobile.py
equity_jenga/api/send_money/queries.py
equity_jenga/api/send_money/to_mobile.py
equity_jenga/api/send_money/within_equity_bank.py
equity_jenga/tests/__init__.py
equity_jenga_api-0.0.7.dist-info/LICENSE
equity_jenga_api-0.0.7.dist-info/METADATA
equity_jenga_api-0.0.7.dist-info/WHEEL
equity_jenga_api-0.0.7.dist-info/entry_points.txt
equity_jenga_api-0.0.7.dist-info/pbr.json
equity_jenga_api-0.0.7.dist-info/top_level.txt
equity_jenga_api-0.0.7.dist-info/RECORD
